{
  "workspaces": [
    {
      "id": "ws-ch-1782386329054",
      "status": "done",
      "video_id": "XnxI_y26e-I",
      "channel_id": "ch1779678163236",
      "title": "TÔI GHÉT CÂY , VÀ NÓ CŨNG THẾ ! ! !  Tree hate you  MB3R",
      "downloadedPath": "XnxI_y26e-I_20260625_111849.mp4",
      "downloadedAt": 1782386338889,
      "downloadStartedAt": 1782386329075,
      "createdAt": 1782386329055,
      "publishedAt": 1782386325000,
      "trimStart": 0.0,
      "trimEnd": 300.0,
      "videoSpeed": 1.2,
      "fpsTarget": 30,
      "exportResolution": "720p",
      "isShort": true,
      "autoRender": true,
      "progress": null,
      "error": null,
      "availableFormats": null,
      "channelName": "Zilk Kay",
      "renderedPath": "TÔI GHÉT CÂY , VÀ NÓ CŨNG THẾ ! ! !  Tree hate you  MB3R.mp4",
      "thumbnailLocal": "media/Zilk Kay/thumbnails/XnxI_y26e-I.jpg",
      "fileSize": 20036998,
      "downloadSpeed": null,
      "downloadTime": null,
      "durationSec": 300,
      "quality": 360,
      "originalDurationSec": 0,
      "originalQuality": 360,
      "renderFps": 146.0,
      "renderWorkers": 4,
      "renderPreset": "p1",
      "renderCodec": "h264_nvenc",
      "renderDurationSec": 53.4634527,
      "bottomBarColor": null
    },
    {
      "id": "ws-user-verify",
      "status": "done",
      "video_id": "MPH4jIzi0hU",
      "channel_id": "ch1778770285853",
      "title": "TÔI GHÉT CÂY TEST RENDER",
      "downloadedPath": "media/ch1778770285853/downloads/MPH4jIzi0hU_20260625_111257.mp4",
      "downloadedAt": 1782385977983,
      "downloadStartedAt": 1782385964322,
      "createdAt": 1782385964207,
      "publishedAt": 1782385964207,
      "trimStart": 0.0,
      "trimEnd": 300.0,
      "videoSpeed": 1.2,
      "fpsTarget": 30,
      "exportResolution": "720p",
      "isShort": true,
      "autoRender": true,
      "progress": null,
      "error": null,
      "availableFormats": null,
      "channelName": null,
      "renderedPath": "TÔI GHÉT CÂY TEST RENDER.mp4",
      "thumbnailLocal": "media/ch1778770285853/thumbnails/MPH4jIzi0hU.jpg",
      "fileSize": 21692464,
      "downloadSpeed": null,
      "downloadTime": null,
      "durationSec": 300,
      "quality": 360,
      "originalDurationSec": 300,
      "originalQuality": 360,
      "renderFps": 414.0,
      "renderWorkers": 4,
      "renderPreset": "p1",
      "renderCodec": "h264_nvenc",
      "renderDurationSec": 19.266243,
      "bottomBarColor": null
    },
    {
      "id": "ws-test-dl-1782385523-part2",
      "status": "done",
      "video_id": "EqWMOrNVnjU",
      "channel_id": "ch1778770285853",
      "title": "Test Split 60s Video (Part 2)",
      "downloadedPath": "media/ch1778770285853/downloads/EqWMOrNVnjU_20260625_110529.mp4",
      "downloadedAt": 1782385529923,
      "downloadStartedAt": 1782385524264,
      "createdAt": 1782385523757,
      "publishedAt": 1782385523757,
      "trimStart": 30.0,
      "trimEnd": 60.0,
      "videoSpeed": 1.2,
      "fpsTarget": 30,
      "exportResolution": "1080p",
      "isShort": true,
      "autoRender": true,
      "progress": null,
      "error": null,
      "availableFormats": null,
      "channelName": null,
      "renderedPath": "part 2.mp4",
      "thumbnailLocal": "media/ch1778770285853/thumbnails/EqWMOrNVnjU.jpg",
      "fileSize": 3882180,
      "downloadSpeed": null,
      "downloadTime": null,
      "durationSec": 60,
      "quality": 360,
      "originalDurationSec": 60,
      "originalQuality": 360,
      "renderFps": 209.0,
      "renderWorkers": 4,
      "renderPreset": "p1",
      "renderCodec": "h264_nvenc",
      "renderDurationSec": 5.1046073,
      "bottomBarColor": null
    },
    {
      "id": "ws-test-dl-1782385523-part1",
      "status": "done",
      "video_id": "EqWMOrNVnjU",
      "channel_id": "ch1778770285853",
      "title": "Test Split 60s Video (Part 1)",
      "downloadedPath": "media/ch1778770285853/downloads/EqWMOrNVnjU_20260625_110529.mp4",
      "downloadedAt": 1782385529923,
      "downloadStartedAt": 1782385524264,
      "createdAt": 1782385523757,
      "publishedAt": 1782385523757,
      "trimStart": 0.0,
      "trimEnd": 30.0,
      "videoSpeed": 1.2,
      "fpsTarget": 30,
      "exportResolution": "1080p",
      "isShort": true,
      "autoRender": true,
      "progress": null,
      "error": null,
      "availableFormats": null,
      "channelName": null,
      "renderedPath": "part 1.mp4",
      "thumbnailLocal": "media/ch1778770285853/thumbnails/EqWMOrNVnjU.jpg",
      "fileSize": 3882180,
      "downloadSpeed": null,
      "downloadTime": null,
      "durationSec": 60,
      "quality": 360,
      "originalDurationSec": 60,
      "originalQuality": 360,
      "renderFps": 121.0,
      "renderWorkers": 4,
      "renderPreset": "p1",
      "renderCodec": "h264_nvenc",
      "renderDurationSec": 7.8195924,
      "bottomBarColor": null
    },
    {
      "id": "ws-test-dl-1782385523",
      "status": "done",
      "video_id": "EqWMOrNVnjU",
      "channel_id": "ch1778770285853",
      "title": "Test Split 60s Video",
      "downloadedPath": "media/ch1778770285853/downloads/EqWMOrNVnjU_20260625_110529.mp4",
      "downloadedAt": 1782385529923,
      "downloadStartedAt": 1782385524264,
      "createdAt": 1782385523757,
      "publishedAt": 1782385523757,
      "trimStart": 0.0,
      "trimEnd": 60.0,
      "videoSpeed": 1.2,
      "fpsTarget": 30,
      "exportResolution": "720p",
      "isShort": true,
      "autoRender": true,
      "progress": null,
      "error": null,
      "availableFormats": null,
      "channelName": null,
      "renderedPath": "Test Split 60s Video.mp4",
      "thumbnailLocal": "media/ch1778770285853/thumbnails/EqWMOrNVnjU.jpg",
      "fileSize": 3882180,
      "downloadSpeed": null,
      "downloadTime": null,
      "durationSec": 60,
      "quality": 360,
      "originalDurationSec": 60,
      "originalQuality": 360,
      "renderFps": 196.0,
      "renderWorkers": 4,
      "renderPreset": "p1",
      "renderCodec": "h264_nvenc",
      "renderDurationSec": 9.1966641,
      "bottomBarColor": null
    },
    {
      "id": "ws-test-dl-1782384961-part2",
      "status": "done",
      "video_id": "EqWMOrNVnjU",
      "channel_id": "ch1778770285853",
      "title": "Test Split 60s Video (Part 2)",
      "downloadedPath": "media/ch1778770285853/downloads/EqWMOrNVnjU_20260625_105608.mp4",
      "downloadedAt": 1782384968513,
      "downloadStartedAt": 1782384962150,
      "createdAt": 1782384961625,
      "publishedAt": 1782384961625,
      "trimStart": 30.0,
      "trimEnd": 60.0,
      "videoSpeed": 1.2,
      "fpsTarget": 30,
      "exportResolution": "1080p",
      "isShort": true,
      "autoRender": true,
      "progress": null,
      "error": null,
      "availableFormats": null,
      "channelName": null,
      "renderedPath": "part 2.mp4",
      "thumbnailLocal": "media/ch1778770285853/thumbnails/EqWMOrNVnjU.jpg",
      "fileSize": 3501888,
      "downloadSpeed": null,
      "downloadTime": null,
      "durationSec": 60,
      "quality": 360,
      "originalDurationSec": 60,
      "originalQuality": 360,
      "renderFps": 166.0,
      "renderWorkers": 4,
      "renderPreset": "p1",
      "renderCodec": "h264_nvenc",
      "renderDurationSec": 7.1295721,
      "bottomBarColor": null
    },
    {
      "id": "ws-test-dl-1782384961-part1",
      "status": "done",
      "video_id": "EqWMOrNVnjU",
      "channel_id": "ch1778770285853",
      "title": "Test Split 60s Video (Part 1)",
      "downloadedPath": "media/ch1778770285853/downloads/EqWMOrNVnjU_20260625_105608.mp4",
      "downloadedAt": 1782384968513,
      "downloadStartedAt": 1782384962150,
      "createdAt": 1782384961625,
      "publishedAt": 1782384961625,
      "trimStart": 0.0,
      "trimEnd": 30.0,
      "videoSpeed": 1.2,
      "fpsTarget": 30,
      "exportResolution": "1080p",
      "isShort": true,
      "autoRender": true,
      "progress": null,
      "error": null,
      "availableFormats": null,
      "channelName": null,
      "renderedPath": "part 1.mp4",
      "thumbnailLocal": "media/ch1778770285853/thumbnails/EqWMOrNVnjU.jpg",
      "fileSize": 3501888,
      "downloadSpeed": null,
      "downloadTime": null,
      "durationSec": 60,
      "quality": 360,
      "originalDurationSec": 60,
      "originalQuality": 360,
      "renderFps": 138.0,
      "renderWorkers": 4,
      "renderPreset": "p1",
      "renderCodec": "h264_nvenc",
      "renderDurationSec": 6.9870734,
      "bottomBarColor": null
    },
    {
      "id": "ws-test-dl-1782384961",
      "status": "done",
      "video_id": "EqWMOrNVnjU",
      "channel_id": "ch1778770285853",
      "title": "Test Split 60s Video",
      "downloadedPath": "media/ch1778770285853/downloads/EqWMOrNVnjU_20260625_105608.mp4",
      "downloadedAt": 1782384968513,
      "downloadStartedAt": 1782384962150,
      "createdAt": 1782384961625,
      "publishedAt": 1782384961625,
      "trimStart": 0.0,
      "trimEnd": 60.0,
      "videoSpeed": 1.2,
      "fpsTarget": 30,
      "exportResolution": "720p",
      "isShort": true,
      "autoRender": true,
      "progress": null,
      "error": null,
      "availableFormats": null,
      "channelName": null,
      "renderedPath": "Test Split 60s Video.mp4",
      "thumbnailLocal": "media/ch1778770285853/thumbnails/EqWMOrNVnjU.jpg",
      "fileSize": 3501888,
      "downloadSpeed": null,
      "downloadTime": null,
      "durationSec": 60,
      "quality": 360,
      "originalDurationSec": 60,
      "originalQuality": 360,
      "renderFps": 217.0,
      "renderWorkers": 4,
      "renderPreset": "p1",
      "renderCodec": "h264_nvenc",
      "renderDurationSec": 8.6738178,
      "bottomBarColor": null
    },
    {
      "id": "ws-ch-1782373163705",
      "status": "done",
      "video_id": "MPH4jIzi0hU",
      "channel_id": "ch1778770285853",
      "title": "TÔI GHÉT CÂY , VÀ NÓ CŨNG THẾ ! ! !  Tree hate you  MB3R",
      "downloadedPath": "media/Nhật Đức Anh Bùi/downloads/MPH4jIzi0hU_20260625_073931.mp4",
      "downloadedAt": 1782373171598,
      "downloadStartedAt": 1782373163722,
      "createdAt": 1782373163705,
      "publishedAt": 1782373161000,
      "trimStart": 0.0,
      "trimEnd": 300.0,
      "videoSpeed": 1.2,
      "fpsTarget": 30,
      "exportResolution": "720p",
      "isShort": true,
      "autoRender": true,
      "progress": null,
      "error": null,
      "availableFormats": null,
      "channelName": "Nhật Đức Anh Bùi",
      "renderedPath": "TÔI GHÉT CÂY , VÀ NÓ CŨNG THẾ ! ! !  Tree hate you  MB3R.mp4",
      "thumbnailLocal": "media/Nhật Đức Anh Bùi/thumbnails/MPH4jIzi0hU.jpg",
      "fileSize": 21354208,
      "downloadSpeed": null,
      "downloadTime": null,
      "durationSec": 300,
      "quality": 360,
      "originalDurationSec": 0,
      "originalQuality": 360,
      "renderFps": 969.0,
      "renderWorkers": 4,
      "renderPreset": "p1",
      "renderCodec": "h264_nvenc",
      "renderDurationSec": 11.3005523,
      "bottomBarColor": null
    },
    {
      "id": "ws-ch-1782373124522",
      "status": "done",
      "video_id": "aRsM4G3T5uo",
      "channel_id": "ch1779678163236",
      "title": "TÔI GHÉT CÂY , VÀ NÓ CŨNG THẾ ! ! !  Tree hate you  MB3R",
      "downloadedPath": "media/Zilk Kay/downloads/aRsM4G3T5uo_20260625_073853.mp4",
      "downloadedAt": 1782373133137,
      "downloadStartedAt": 1782373124539,
      "createdAt": 1782373124523,
      "publishedAt": 1782373120000,
      "trimStart": 0.0,
      "trimEnd": 300.0,
      "videoSpeed": 1.2,
      "fpsTarget": 30,
      "exportResolution": "720p",
      "isShort": true,
      "autoRender": true,
      "progress": null,
      "error": null,
      "availableFormats": null,
      "channelName": "Zilk Kay",
      "renderedPath": "TÔI GHÉT CÂY , VÀ NÓ CŨNG THẾ ! ! !  Tree hate you  MB3R.mp4",
      "thumbnailLocal": "media/Zilk Kay/thumbnails/aRsM4G3T5uo.jpg",
      "fileSize": 19607340,
      "downloadSpeed": null,
      "downloadTime": null,
      "durationSec": 300,
      "quality": 360,
      "originalDurationSec": 0,
      "originalQuality": 360,
      "renderFps": 1015.0,
      "renderWorkers": 4,
      "renderPreset": "p1",
      "renderCodec": "h264_nvenc",
      "renderDurationSec": 10.546165,
      "bottomBarColor": null
    },
    {
      "id": "ws-ch-1782372818865",
      "status": "done",
      "video_id": "UCMyV8NXRh0",
      "channel_id": "ch1779678163236",
      "title": "TÔI GHÉT CÂY , VÀ NÓ CŨNG THẾ ! ! !  Tree hate you  MB3R",
      "downloadedPath": "media/Zilk Kay/downloads/UCMyV8NXRh0_20260625_073349.mp4",
      "downloadedAt": 1782372829981,
      "downloadStartedAt": 1782372818887,
      "createdAt": 1782372818865,
      "publishedAt": 1782369098000,
      "trimStart": 0.0,
      "trimEnd": 300.0,
      "videoSpeed": 1.2,
      "fpsTarget": 30,
      "exportResolution": "720p",
      "isShort": true,
      "autoRender": true,
      "progress": null,
      "error": null,
      "availableFormats": null,
      "channelName": "Zilk Kay",
      "renderedPath": "TÔI GHÉT CÂY , VÀ NÓ CŨNG THẾ ! ! !  Tree hate you  MB3R.mp4",
      "thumbnailLocal": "media/Zilk Kay/thumbnails/UCMyV8NXRh0.jpg",
      "fileSize": 20517902,
      "downloadSpeed": null,
      "downloadTime": null,
      "durationSec": 300,
      "quality": 360,
      "originalDurationSec": 0,
      "originalQuality": 360,
      "renderFps": 558.0,
      "renderWorkers": 4,
      "renderPreset": "p1",
      "renderCodec": "h264_nvenc",
      "renderDurationSec": 18.0521952,
      "bottomBarColor": null
    },
    {
      "id": "ws-test-dl-1782371044-part2",
      "status": "done",
      "video_id": "EqWMOrNVnjU",
      "channel_id": "ch1778770285853",
      "title": "Test Split 60s Video (Part 2)",
      "downloadedPath": "media/ch1778770285853/downloads/EqWMOrNVnjU_20260625_070440.mp4",
      "downloadedAt": 1782371080792,
      "downloadStartedAt": 1782371046520,
      "createdAt": 1782371044480,
      "publishedAt": 1782371044480,
      "trimStart": 30.0,
      "trimEnd": 60.0,
      "videoSpeed": 1.2,
      "fpsTarget": 30,
      "exportResolution": "1080p",
      "isShort": true,
      "autoRender": true,
      "progress": null,
      "error": null,
      "availableFormats": null,
      "channelName": null,
      "renderedPath": "part 2.mp4",
      "thumbnailLocal": "media/ch1778770285853/thumbnails/EqWMOrNVnjU.jpg",
      "fileSize": 13662504,
      "downloadSpeed": null,
      "downloadTime": null,
      "durationSec": 60,
      "quality": 720,
      "originalDurationSec": 60,
      "originalQuality": 1080,
      "renderFps": 383.0,
      "renderWorkers": 4,
      "renderPreset": "p1",
      "renderCodec": "h264_nvenc",
      "renderDurationSec": 4.5262793,
      "bottomBarColor": null
    },
    {
      "id": "ws-test-dl-1782371044-part1",
      "status": "done",
      "video_id": "EqWMOrNVnjU",
      "channel_id": "ch1778770285853",
      "title": "Test Split 60s Video (Part 1)",
      "downloadedPath": "media/ch1778770285853/downloads/EqWMOrNVnjU_20260625_070440.mp4",
      "downloadedAt": 1782371080792,
      "downloadStartedAt": 1782371046520,
      "createdAt": 1782371044480,
      "publishedAt": 1782371044480,
      "trimStart": 0.0,
      "trimEnd": 30.0,
      "videoSpeed": 1.2,
      "fpsTarget": 30,
      "exportResolution": "1080p",
      "isShort": true,
      "autoRender": true,
      "progress": null,
      "error": null,
      "availableFormats": null,
      "channelName": null,
      "renderedPath": "part 1.mp4",
      "thumbnailLocal": "media/ch1778770285853/thumbnails/EqWMOrNVnjU.jpg",
      "fileSize": 13662504,
      "downloadSpeed": null,
      "downloadTime": null,
      "durationSec": 60,
      "quality": 720,
      "originalDurationSec": 60,
      "originalQuality": 1080,
      "renderFps": 318.0,
      "renderWorkers": 4,
      "renderPreset": "p1",
      "renderCodec": "h264_nvenc",
      "renderDurationSec": 6.2318014999999995,
      "bottomBarColor": null
    },
    {
      "id": "ws-test-dl-1782371044",
      "status": "done",
      "video_id": "EqWMOrNVnjU",
      "channel_id": "ch1778770285853",
      "title": "Test Split 60s Video",
      "downloadedPath": "media/ch1778770285853/downloads/EqWMOrNVnjU_20260625_070440.mp4",
      "downloadedAt": 1782371080792,
      "downloadStartedAt": 1782371046520,
      "createdAt": 1782371044480,
      "publishedAt": 1782371044480,
      "trimStart": 0.0,
      "trimEnd": 60.0,
      "videoSpeed": 1.2,
      "fpsTarget": 30,
      "exportResolution": "720p",
      "isShort": true,
      "autoRender": true,
      "progress": null,
      "error": null,
      "availableFormats": null,
      "channelName": null,
      "renderedPath": "Test Split 60s Video.mp4",
      "thumbnailLocal": "media/ch1778770285853/thumbnails/EqWMOrNVnjU.jpg",
      "fileSize": 13662504,
      "downloadSpeed": null,
      "downloadTime": null,
      "durationSec": 60,
      "quality": 720,
      "originalDurationSec": 60,
      "originalQuality": 1080,
      "renderFps": 465.0,
      "renderWorkers": 4,
      "renderPreset": "p1",
      "renderCodec": "h264_nvenc",
      "renderDurationSec": 7.230543,
      "bottomBarColor": null
    },
    {
      "id": "ws-ch-1782367931548",
      "status": "done",
      "video_id": "XUkh1fiAL10",
      "channel_id": "ch1778770285853",
      "title": "TÔI GHÉT CÂY , VÀ NÓ CŨNG THẾ ! ! !  Tree hate you  MB3R",
      "downloadedPath": "media/Nhật Đức Anh Bùi/downloads/XUkh1fiAL10_20260625_061600.mp4",
      "downloadedAt": 1782368160824,
      "downloadStartedAt": 1782367931561,
      "createdAt": 1782367931549,
      "publishedAt": 1782367903000,
      "trimStart": 0.0,
      "trimEnd": 420.0,
      "videoSpeed": 1.2,
      "fpsTarget": 30,
      "exportResolution": "720p",
      "isShort": true,
      "autoRender": true,
      "progress": null,
      "error": null,
      "availableFormats": null,
      "channelName": "Nhật Đức Anh Bùi",
      "renderedPath": "TÔI GHÉT CÂY , VÀ NÓ CŨNG THẾ ! ! !  Tree hate you  MB3R.mp4",
      "thumbnailLocal": null,
      "fileSize": 117017613,
      "downloadSpeed": null,
      "downloadTime": null,
      "durationSec": 420,
      "quality": 720,
      "originalDurationSec": 0,
      "originalQuality": 1080,
      "renderFps": 392.0,
      "renderWorkers": 4,
      "renderPreset": "p1",
      "renderCodec": "h264_nvenc",
      "renderDurationSec": 29.4755031,
      "bottomBarColor": null
    },
    {
      "id": "ws-ch-1782367926846",
      "status": "done",
      "video_id": "PLFLYEAqZDg",
      "channel_id": "ch1779678163236",
      "title": "TÔI GHÉT CÂY , VÀ NÓ CŨNG THẾ ! ! !  Tree hate you  MB3R",
      "downloadedPath": null,
      "downloadedAt": null,
      "downloadStartedAt": 1782367926858,
      "createdAt": 1782367926846,
      "publishedAt": 1782367866000,
      "trimStart": 0.0,
      "trimEnd": 0.0,
      "videoSpeed": 1.2,
      "fpsTarget": 30,
      "exportResolution": "720p",
      "isShort": true,
      "autoRender": true,
      "progress": null,
      "error": null,
      "availableFormats": null,
      "channelName": "Zilk Kay",
      "renderedPath": "TÔI GHÉT CÂY , VÀ NÓ CŨNG THẾ ! ! !  Tree hate you  MB3R.mp4",
      "thumbnailLocal": null,
      "fileSize": null,
      "downloadSpeed": null,
      "downloadTime": null,
      "durationSec": 0,
      "quality": null,
      "originalDurationSec": 0,
      "originalQuality": null,
      "renderFps": 394.0,
      "renderWorkers": 4,
      "renderPreset": "p1",
      "renderCodec": "h264_nvenc",
      "renderDurationSec": 31.7788239,
      "bottomBarColor": null
    },
    {
      "id": "ws-ch-1782367326719",
      "status": "error",
      "video_id": "ZcI9xJcinb0",
      "channel_id": "ch1778770285853",
      "title": "TÔI GHÉT CÂY , VÀ NÓ CŨNG THẾ ! ! !  Tree hate you  MB3R",
      "downloadedPath": "media/Nhật Đức Anh Bùi/downloads/ZcI9xJcinb0_20260625_060232.mp4",
      "downloadedAt": 1782367352053,
      "downloadStartedAt": 1782367326747,
      "createdAt": 1782367326720,
      "publishedAt": 1782367321000,
      "trimStart": 0.0,
      "trimEnd": 420.0,
      "videoSpeed": 1.2,
      "fpsTarget": 30,
      "exportResolution": "720p",
      "isShort": true,
      "autoRender": true,
      "progress": null,
      "error": "Render bị gián đoạn (Ứng dụng đóng đột ngột)",
      "availableFormats": null,
      "channelName": "Nhật Đức Anh Bùi",
      "renderedPath": null,
      "thumbnailLocal": "media/Nhật Đức Anh Bùi/thumbnails/ZcI9xJcinb0.jpg",
      "fileSize": 137753255,
      "downloadSpeed": null,
      "downloadTime": null,
      "durationSec": 420,
      "quality": 720,
      "originalDurationSec": 0,
      "originalQuality": 1080,
      "renderFps": null,
      "renderWorkers": null,
      "renderPreset": null,
      "renderCodec": null,
      "renderDurationSec": null,
      "bottomBarColor": null
    },
    {
      "id": "ws-ch-1782365723307",
      "status": "done",
      "video_id": "t6nf90UhleM",
      "channel_id": "ch1779678163236",
      "title": "TÔI GHÉT CÂY , VÀ NÓ CŨNG THẾ ! ! !  Tree hate you  MB3R",
      "downloadedPath": "media/Zilk Kay/downloads/t6nf90UhleM_20260625_053550.mp4",
      "downloadedAt": 1782365750556,
      "downloadStartedAt": 1782365723335,
      "createdAt": 1782365723308,
      "publishedAt": 1782365721000,
      "trimStart": 0.0,
      "trimEnd": 420.0,
      "videoSpeed": 1.2,
      "fpsTarget": 30,
      "exportResolution": "720p",
      "isShort": true,
      "autoRender": true,
      "progress": null,
      "error": null,
      "availableFormats": null,
      "channelName": "Zilk Kay",
      "renderedPath": "TÔI GHÉT CÂY , VÀ NÓ CŨNG THẾ ! ! !  Tree hate you  MB3R.mp4",
      "thumbnailLocal": "media/Zilk Kay/thumbnails/t6nf90UhleM.jpg",
      "fileSize": 115997522,
      "downloadSpeed": null,
      "downloadTime": null,
      "durationSec": 420,
      "quality": 720,
      "originalDurationSec": 0,
      "originalQuality": 1080,
      "renderFps": 463.0,
      "renderWorkers": 4,
      "renderPreset": "p1",
      "renderCodec": "h264_nvenc",
      "renderDurationSec": 26.6814627,
      "bottomBarColor": null
    },
    {
      "id": "ws-ch-1782365593272",
      "status": "done",
      "video_id": "mlzHGr9oS2A",
      "channel_id": "ch-1781346484630",
      "title": "TÔI GHÉT CÂY , VÀ NÓ CŨNG THẾ ! ! !  Tree hate you  MB3R",
      "downloadedPath": null,
      "downloadedAt": null,
      "downloadStartedAt": 1782365593693,
      "createdAt": 1782365593422,
      "publishedAt": 1782365592000,
      "trimStart": 0.0,
      "trimEnd": 0.0,
      "videoSpeed": 1.2,
      "fpsTarget": 30,
      "exportResolution": "720p",
      "isShort": true,
      "autoRender": true,
      "progress": null,
      "error": null,
      "availableFormats": null,
      "channelName": "BadyNone",
      "renderedPath": "TÔI GHÉT CÂY , VÀ NÓ CŨNG THẾ ! ! !  Tree hate you  MB3R.mp4",
      "thumbnailLocal": null,
      "fileSize": null,
      "downloadSpeed": null,
      "downloadTime": null,
      "durationSec": 0,
      "quality": null,
      "originalDurationSec": 0,
      "originalQuality": null,
      "renderFps": 357.0,
      "renderWorkers": 4,
      "renderPreset": "p1",
      "renderCodec": "h264_nvenc",
      "renderDurationSec": 34.1963473,
      "bottomBarColor": null
    },
    {
      "id": "ws-ch-1782365592487",
      "status": "done",
      "video_id": "qAh5ibJckPI",
      "channel_id": "ch-1781346484630",
      "title": "TÔI GHÉT CÂY , VÀ NÓ CŨNG THẾ ! ! !  Tree hate you  MB3R",
      "downloadedPath": null,
      "downloadedAt": null,
      "downloadStartedAt": 1782365593243,
      "createdAt": 1782365592507,
      "publishedAt": 1782365592000,
      "trimStart": 0.0,
      "trimEnd": 0.0,
      "videoSpeed": 1.2,
      "fpsTarget": 30,
      "exportResolution": "720p",
      "isShort": true,
      "autoRender": true,
      "progress": null,
      "error": null,
      "availableFormats": null,
      "channelName": "BadyNone",
      "renderedPath": "TÔI GHÉT CÂY , VÀ NÓ CŨNG THẾ ! ! !  Tree hate you  MB3R.mp4",
      "thumbnailLocal": null,
      "fileSize": null,
      "downloadSpeed": null,
      "downloadTime": null,
      "durationSec": 0,
      "quality": null,
      "originalDurationSec": 0,
      "originalQuality": null,
      "renderFps": 355.0,
      "renderWorkers": 4,
      "renderPreset": "p1",
      "renderCodec": "h264_nvenc",
      "renderDurationSec": 35.8196201,
      "bottomBarColor": null
    },
    {
      "id": "ws-ch-1782365592452",
      "status": "done",
      "video_id": "ZfxwcN3o6Js",
      "channel_id": "ch-1781346484630",
      "title": "TÔI GHÉT CÂY , VÀ NÓ CŨNG THẾ ! ! !  Tree hate you  MB3R",
      "downloadedPath": "media/BadyNone/downloads/ZfxwcN3o6Js_20260625_053343.mp4",
      "downloadedAt": 1782365623798,
      "downloadStartedAt": 1782365592486,
      "createdAt": 1782365592466,
      "publishedAt": 1782365592000,
      "trimStart": 0.0,
      "trimEnd": 420.0,
      "videoSpeed": 1.2,
      "fpsTarget": 30,
      "exportResolution": "720p",
      "isShort": true,
      "autoRender": true,
      "progress": null,
      "error": null,
      "availableFormats": null,
      "channelName": "BadyNone",
      "renderedPath": "TÔI GHÉT CÂY , VÀ NÓ CŨNG THẾ ! ! !  Tree hate you  MB3R.mp4",
      "thumbnailLocal": "media/BadyNone/thumbnails/ZfxwcN3o6Js.jpg",
      "fileSize": 116001180,
      "downloadSpeed": null,
      "downloadTime": null,
      "durationSec": 420,
      "quality": 720,
      "originalDurationSec": 0,
      "originalQuality": 1080,
      "renderFps": 336.0,
      "renderWorkers": 4,
      "renderPreset": "p1",
      "renderCodec": "h264_nvenc",
      "renderDurationSec": 64.9131812,
      "bottomBarColor": null
    },
    {
      "id": "ws-ch-1782365592423",
      "status": "done",
      "video_id": "OoAfx_mWQD4",
      "channel_id": "ch-1781346484630",
      "title": "TÔI GHÉT CÂY , VÀ NÓ CŨNG THẾ ! ! !  Tree hate you  MB3R",
      "downloadedPath": null,
      "downloadedAt": null,
      "downloadStartedAt": 1782365592449,
      "createdAt": 1782365592424,
      "publishedAt": 1782365592000,
      "trimStart": 0.0,
      "trimEnd": 0.0,
      "videoSpeed": 1.2,
      "fpsTarget": 30,
      "exportResolution": "720p",
      "isShort": true,
      "autoRender": true,
      "progress": null,
      "error": null,
      "availableFormats": null,
      "channelName": "BadyNone",
      "renderedPath": "TÔI GHÉT CÂY , VÀ NÓ CŨNG THẾ ! ! !  Tree hate you  MB3R.mp4",
      "thumbnailLocal": null,
      "fileSize": null,
      "downloadSpeed": null,
      "downloadTime": null,
      "durationSec": 0,
      "quality": null,
      "originalDurationSec": 0,
      "originalQuality": null,
      "renderFps": 336.0,
      "renderWorkers": 4,
      "renderPreset": "p1",
      "renderCodec": "h264_nvenc",
      "renderDurationSec": 67.2118684,
      "bottomBarColor": null
    },
    {
      "id": "ws-ch-1782364905915",
      "status": "error",
      "video_id": "cOKrz1P-pak",
      "channel_id": "ch-1781346484630",
      "title": "TÔI GHÉT CÂY , VÀ NÓ CŨNG THẾ ! ! !  Tree hate you  MB3R ( G1 )",
      "downloadedPath": null,
      "downloadedAt": null,
      "downloadStartedAt": 1782364905945,
      "createdAt": 1782364905930,
      "publishedAt": 1782364905000,
      "trimStart": 0.0,
      "trimEnd": 0.0,
      "videoSpeed": 1.2,
      "fpsTarget": 30,
      "exportResolution": "720p",
      "isShort": true,
      "autoRender": true,
      "progress": null,
      "error": "Tải xuống bị gián đoạn (Ứng dụng đóng đột ngột)",
      "availableFormats": null,
      "channelName": "BadyNone",
      "renderedPath": null,
      "thumbnailLocal": null,
      "fileSize": null,
      "downloadSpeed": null,
      "downloadTime": null,
      "durationSec": 0,
      "quality": null,
      "originalDurationSec": 0,
      "originalQuality": null,
      "renderFps": null,
      "renderWorkers": null,
      "renderPreset": null,
      "renderCodec": null,
      "renderDurationSec": null,
      "bottomBarColor": null
    },
    {
      "id": "ws-ch-1782364905894",
      "status": "error",
      "video_id": "qvI3AiCg-Sk",
      "channel_id": "ch-1781346484630",
      "title": "TÔI GHÉT CÂY , VÀ NÓ CŨNG THẾ ! ! !  Tree hate you  MB3R",
      "downloadedPath": null,
      "downloadedAt": null,
      "downloadStartedAt": 1782364905914,
      "createdAt": 1782364905894,
      "publishedAt": 1782364905000,
      "trimStart": 0.0,
      "trimEnd": 0.0,
      "videoSpeed": 1.2,
      "fpsTarget": 30,
      "exportResolution": "720p",
      "isShort": true,
      "autoRender": true,
      "progress": null,
      "error": "Tải xuống bị gián đoạn (Ứng dụng đóng đột ngột)",
      "availableFormats": null,
      "channelName": "BadyNone",
      "renderedPath": null,
      "thumbnailLocal": null,
      "fileSize": null,
      "downloadSpeed": null,
      "downloadTime": null,
      "durationSec": 0,
      "quality": null,
      "originalDurationSec": 0,
      "originalQuality": null,
      "renderFps": null,
      "renderWorkers": null,
      "renderPreset": null,
      "renderCodec": null,
      "renderDurationSec": null,
      "bottomBarColor": null
    },
    {
      "id": "ws-ch-1782363973987",
      "status": "error",
      "video_id": "uPqi08MBu20",
      "channel_id": "ch1779678163236",
      "title": "TÔI GHÉT CÂY , VÀ NÓ CŨNG THẾ ! ! !  Tree hate you  MB3R",
      "downloadedPath": "media/Zilk Kay/downloads/uPqi08MBu20_20260625_050643.mp4",
      "downloadedAt": 1782364003070,
      "downloadStartedAt": 1782363974001,
      "createdAt": 1782363973987,
      "publishedAt": 1782363973000,
      "trimStart": 0.0,
      "trimEnd": 420.0,
      "videoSpeed": 1.2,
      "fpsTarget": 30,
      "exportResolution": "720p",
      "isShort": true,
      "autoRender": true,
      "progress": null,
      "error": "Render bị gián đoạn (Ứng dụng đóng đột ngột)",
      "availableFormats": null,
      "channelName": "Zilk Kay",
      "renderedPath": null,
      "thumbnailLocal": "media/Zilk Kay/thumbnails/uPqi08MBu20.jpg",
      "fileSize": 138919017,
      "downloadSpeed": null,
      "downloadTime": null,
      "durationSec": 420,
      "quality": 720,
      "originalDurationSec": 0,
      "originalQuality": 1080,
      "renderFps": null,
      "renderWorkers": null,
      "renderPreset": null,
      "renderCodec": null,
      "renderDurationSec": null,
      "bottomBarColor": null
    },
    {
      "id": "ws-ch-1782363582749",
      "status": "done",
      "video_id": "P3tYnFBXL9g",
      "channel_id": "ch1779678163236",
      "title": "TÔI GHÉT CÂY , VÀ NÓ CŨNG THẾ ! ! !  Tree hate you  MB3R",
      "downloadedPath": "media/Zilk Kay/downloads/P3tYnFBXL9g_20260625_050009.mp4",
      "downloadedAt": 1782363609462,
      "downloadStartedAt": 1782363582767,
      "createdAt": 1782363582750,
      "publishedAt": 1782363575000,
      "trimStart": 0.0,
      "trimEnd": 420.0,
      "videoSpeed": 1.2,
      "fpsTarget": 30,
      "exportResolution": "720p",
      "isShort": true,
      "autoRender": true,
      "progress": null,
      "error": null,
      "availableFormats": null,
      "channelName": "Zilk Kay",
      "renderedPath": "TÔI GHÉT CÂY , VÀ NÓ CŨNG THẾ ! ! !  Tree hate you  MB3R.mp4",
      "thumbnailLocal": "media/Zilk Kay/thumbnails/P3tYnFBXL9g.jpg",
      "fileSize": 138919017,
      "downloadSpeed": null,
      "downloadTime": null,
      "durationSec": 420,
      "quality": 720,
      "originalDurationSec": 0,
      "originalQuality": 1080,
      "renderFps": 318.0,
      "renderWorkers": 4,
      "renderPreset": "p1",
      "renderCodec": "h264_nvenc",
      "renderDurationSec": 37.6863644,
      "bottomBarColor": null
    },
    {
      "id": "ws-ch-1782362846033",
      "status": "done",
      "video_id": "EitZ7AiduZY",
      "channel_id": "ch1779678163236",
      "title": "TÔI GHÉT CÂY , VÀ NÓ CŨNG THẾ ! ! !  Tree hate you  MB3R",
      "downloadedPath": "media/Zilk Kay/downloads/EitZ7AiduZY_20260625_044807.mp4",
      "downloadedAt": 1782362887858,
      "downloadStartedAt": 1782362846063,
      "createdAt": 1782362846034,
      "publishedAt": 1782362844000,
      "trimStart": 0.0,
      "trimEnd": 420.0,
      "videoSpeed": 1.2,
      "fpsTarget": 30,
      "exportResolution": "720p",
      "isShort": true,
      "autoRender": true,
      "progress": null,
      "error": null,
      "availableFormats": null,
      "channelName": "Zilk Kay",
      "renderedPath": "TÔI GHÉT CÂY , VÀ NÓ CŨNG THẾ ! ! !  Tree hate you  MB3R.mp4",
      "thumbnailLocal": "media/Zilk Kay/thumbnails/EitZ7AiduZY.jpg",
      "fileSize": 138722091,
      "downloadSpeed": null,
      "downloadTime": null,
      "durationSec": 420,
      "quality": 720,
      "originalDurationSec": 0,
      "originalQuality": 1080,
      "renderFps": 351.0,
      "renderWorkers": 4,
      "renderPreset": "p1",
      "renderCodec": "h264_nvenc",
      "renderDurationSec": 35.7557677,
      "bottomBarColor": null
    },
    {
      "id": "ws-ch-1782362268904",
      "status": "done",
      "video_id": "_cmvPypFRNA",
      "channel_id": "ch1779678163236",
      "title": "TÔI GHÉT CÂY , VÀ NÓ CŨNG THẾ ! ! !  Tree hate you  MB3R",
      "downloadedPath": "media/Zilk Kay/downloads/_cmvPypFRNA_20260625_043831.mp4",
      "downloadedAt": 1782362311193,
      "downloadStartedAt": 1782362268937,
      "createdAt": 1782362268904,
      "publishedAt": 1782362259000,
      "trimStart": 0.0,
      "trimEnd": 420.0,
      "videoSpeed": 1.2,
      "fpsTarget": 30,
      "exportResolution": "720p",
      "isShort": true,
      "autoRender": true,
      "progress": null,
      "error": null,
      "availableFormats": null,
      "channelName": "Zilk Kay",
      "renderedPath": "TÔI GHÉT CÂY , VÀ NÓ CŨNG THẾ ! ! !  Tree hate you  MB3R.mp4",
      "thumbnailLocal": "media/Zilk Kay/thumbnails/_cmvPypFRNA.jpg",
      "fileSize": 138728210,
      "downloadSpeed": null,
      "downloadTime": null,
      "durationSec": 420,
      "quality": 720,
      "originalDurationSec": 0,
      "originalQuality": 1080,
      "renderFps": 224.0,
      "renderWorkers": 4,
      "renderPreset": "p1",
      "renderCodec": "h264_nvenc",
      "renderDurationSec": 53.1560592,
      "bottomBarColor": null
    },
    {
      "id": "ws-ch-1782361977030",
      "status": "done",
      "video_id": "OFsWxbgdEOE",
      "channel_id": "ch1779678163236",
      "title": "TÔI GHÉT CÂY , VÀ NÓ CŨNG THẾ ! ! !  Tree hate you  MB3R",
      "downloadedPath": "media/Zilk Kay/downloads/OFsWxbgdEOE_20260625_043327.mp4",
      "downloadedAt": 1782362007616,
      "downloadStartedAt": 1782361977054,
      "createdAt": 1782361977030,
      "publishedAt": 1782361977000,
      "trimStart": 0.0,
      "trimEnd": 420.0,
      "videoSpeed": 1.2,
      "fpsTarget": 30,
      "exportResolution": "720p",
      "isShort": true,
      "autoRender": true,
      "progress": null,
      "error": null,
      "availableFormats": null,
      "channelName": "Zilk Kay",
      "renderedPath": "TÔI GHÉT CÂY , VÀ NÓ CŨNG THẾ ! ! !  Tree hate you  MB3R.mp4",
      "thumbnailLocal": "media/Zilk Kay/thumbnails/OFsWxbgdEOE.jpg",
      "fileSize": 115803386,
      "downloadSpeed": null,
      "downloadTime": null,
      "durationSec": 420,
      "quality": 720,
      "originalDurationSec": 0,
      "originalQuality": 1080,
      "renderFps": 341.0,
      "renderWorkers": 4,
      "renderPreset": "p1",
      "renderCodec": "h264_nvenc",
      "renderDurationSec": 35.4600326,
      "bottomBarColor": null
    },
    {
      "id": "ws-ch-1782361923563",
      "status": "done",
      "video_id": "237_3jyA-Ns",
      "channel_id": "ch1778770285853",
      "title": "TÔI GHÉT CÂY , VÀ NÓ CŨNG THẾ ! ! !  Tree hate you  MB3R ( F2 )",
      "downloadedPath": "media/Nhật Đức Anh Bùi/downloads/237_3jyA-Ns_20260625_043229.mp4",
      "downloadedAt": 1782361949808,
      "downloadStartedAt": 1782361923595,
      "createdAt": 1782361923564,
      "publishedAt": 1782361923000,
      "trimStart": 0.0,
      "trimEnd": 420.0,
      "videoSpeed": 1.2,
      "fpsTarget": 30,
      "exportResolution": "720p",
      "isShort": true,
      "autoRender": true,
      "progress": null,
      "error": null,
      "availableFormats": null,
      "channelName": "Nhật Đức Anh Bùi",
      "renderedPath": "TÔI GHÉT CÂY , VÀ NÓ CŨNG THẾ ! ! !  Tree hate you  MB3R ( F2 ).mp4",
      "thumbnailLocal": "media/Nhật Đức Anh Bùi/thumbnails/237_3jyA-Ns.jpg",
      "fileSize": 115803386,
      "downloadSpeed": null,
      "downloadTime": null,
      "durationSec": 420,
      "quality": 720,
      "originalDurationSec": 0,
      "originalQuality": 1080,
      "renderFps": 370.0,
      "renderWorkers": 4,
      "renderPreset": "p1",
      "renderCodec": "h264_nvenc",
      "renderDurationSec": 36.9857379,
      "bottomBarColor": null
    },
    {
      "id": "ws-ch-1781373936114",
      "status": "done",
      "video_id": "OzdXWb2Zc6Y",
      "channel_id": "ch1779678163236",
      "title": "TÔI GHÉT CÂY , VÀ NÓ CŨNG THẾ ! ! !  Tree hate you  MB3R",
      "downloadedPath": "media/Zilk Kay/downloads/OzdXWb2Zc6Y_20260613_180820.mp4",
      "downloadedAt": 1781374100516,
      "downloadStartedAt": null,
      "createdAt": 1781373936115,
      "publishedAt": 1781373932000,
      "trimStart": 0.0,
      "trimEnd": 5.0,
      "videoSpeed": 1.2,
      "fpsTarget": 30,
      "exportResolution": "720p",
      "isShort": true,
      "autoRender": true,
      "progress": null,
      "error": null,
      "availableFormats": null,
      "channelName": "Zilk Kay",
      "renderedPath": "TÔI GHÉT CÂY , VÀ NÓ CŨNG THẾ ! ! !  Tree hate you  MB3R.mp4",
      "thumbnailLocal": "media/Zilk Kay/thumbnails/OzdXWb2Zc6Y.jpg",
      "fileSize": null,
      "downloadSpeed": null,
      "downloadTime": null,
      "durationSec": 5,
      "quality": null,
      "originalDurationSec": null,
      "originalQuality": null,
      "renderFps": 0.0,
      "renderWorkers": 4,
      "renderPreset": "p1",
      "renderCodec": "h264_nvenc",
      "renderDurationSec": 4.213514,
      "bottomBarColor": null
    }
  ]
}